{
  "api": {
    "search": "https://www.googleapis.com/youtube/v3/search",
    "video": "https://www.googleapis.com/youtube/v3/videos",
    "channel": "https://www.googleapis.com/youtube/v3/channels",
    "category": "https://www.googleapis.com/youtube/v3/videoCategories"
  },
  "args": {
    "search": {
      "part": "snippet",
      "q": "",
      "type": "video",
      "maxResults": 25,
      "key": "AIzaSyBVPQgk-mlDVX5kNDck5fvlgo54qvQt0oA"
    },
    "video": {
      "part": "snippet,contentDetails,statistics,liveStreamingDetails,player,recordingDetails,status,topicDetails",
      "key": "AIzaSyBVPQgk-mlDVX5kNDck5fvlgo54qvQt0oA"
    },
    "channel": {
      "part": "snippet,contentDetails,statistics,brandingSettings,status,topicDetails",
      "key": "AIzaSyBVPQgk-mlDVX5kNDck5fvlgo54qvQt0oA"
    },
    "category": {
      "part": "snippet",
      "key": "AIzaSyBVPQgk-mlDVX5kNDck5fvlgo54qvQt0oA"
    }
  }
}




